ovos_plugin_common_play/__init__.py
ovos_plugin_common_play/launcher.py
ovos_plugin_common_play/version.py
ovos_plugin_common_play/ocp/__init__.py
ovos_plugin_common_play/ocp/base.py
ovos_plugin_common_play/ocp/constants.py
ovos_plugin_common_play/ocp/gui.py
ovos_plugin_common_play/ocp/media.py
ovos_plugin_common_play/ocp/mpris.py
ovos_plugin_common_play/ocp/player.py
ovos_plugin_common_play/ocp/search.py
ovos_plugin_common_play/ocp/status.py
ovos_plugin_common_play/ocp/utils.py
ovos_plugin_common_play/ocp/res/gui/OCP.png
ovos_plugin_common_play/ocp/res/gui/qt5/AudioPlayerControl.qml
ovos_plugin_common_play/ocp/res/gui/qt5/ConfigDelegateLayoutItem.qml
ovos_plugin_common_play/ocp/res/gui/qt5/ConfigOptionDelegate.qml
ovos_plugin_common_play/ocp/res/gui/qt5/ConfigSliderDelegate.qml
ovos_plugin_common_play/ocp/res/gui/qt5/ConfigSwitchDelegate.qml
ovos_plugin_common_play/ocp/res/gui/qt5/Disambiguation.qml
ovos_plugin_common_play/ocp/res/gui/qt5/GenericCloseControl.qml
ovos_plugin_common_play/ocp/res/gui/qt5/Home.qml
ovos_plugin_common_play/ocp/res/gui/qt5/NowPlayingHomeBar.qml
ovos_plugin_common_play/ocp/res/gui/qt5/OCPSkillsView.qml
ovos_plugin_common_play/ocp/res/gui/qt5/OVOSSeekControl.qml
ovos_plugin_common_play/ocp/res/gui/qt5/OVOSSeekControlQtAv.qml
ovos_plugin_common_play/ocp/res/gui/qt5/OVOSSyncPlayer.qml
ovos_plugin_common_play/ocp/res/gui/qt5/OVOSVideoPlayer.qml
ovos_plugin_common_play/ocp/res/gui/qt5/OVOSVideoPlayerQtAv.qml
ovos_plugin_common_play/ocp/res/gui/qt5/OVOSWebPlayer.qml
ovos_plugin_common_play/ocp/res/gui/qt5/PlayerLoader.qml
ovos_plugin_common_play/ocp/res/gui/qt5/Playlist.qml
ovos_plugin_common_play/ocp/res/gui/qt5/Search.qml
ovos_plugin_common_play/ocp/res/gui/qt5/SuggestionsView.qml
ovos_plugin_common_play/ocp/res/gui/qt5/VideoPlayerControl.qml
ovos_plugin_common_play/ocp/res/gui/qt5/busy.qml
ovos_plugin_common_play/ocp/res/gui/qt5/qmldir
ovos_plugin_common_play/ocp/res/gui/qt5/+mediacenter/AudioPlayerControl.qml
ovos_plugin_common_play-1.2.1.dist-info/LICENSE
ovos_plugin_common_play-1.2.1.dist-info/METADATA
ovos_plugin_common_play-1.2.1.dist-info/WHEEL
ovos_plugin_common_play-1.2.1.dist-info/entry_points.txt
ovos_plugin_common_play-1.2.1.dist-info/top_level.txt
ovos_plugin_common_play-1.2.1.dist-info/zip-safe
ovos_plugin_common_play-1.2.1.dist-info/RECORD
