Metadata-Version: 2.1
Name: ovos-plugin-common-play
Version: 1.2.1
Summary: OVOS common play audio service adapter plugin
Home-page: https://github.com/OpenVoiceOS/ovos-ocp-audio-plugin
Author: JarbasAi
Author-email: jarbasai@mailfence.com
License: Apache-2.0
Keywords: ovos audio plugin
Classifier: Development Status :: 3 - Alpha
Classifier: Intended Audience :: Developers
Classifier: Topic :: Text Processing :: Linguistic
Classifier: License :: OSI Approved :: Apache Software License
Classifier: Programming Language :: Python :: 2
Classifier: Programming Language :: Python :: 2.7
Classifier: Programming Language :: Python :: 3
Classifier: Programming Language :: Python :: 3.0
Classifier: Programming Language :: Python :: 3.1
Classifier: Programming Language :: Python :: 3.2
Classifier: Programming Language :: Python :: 3.3
Classifier: Programming Language :: Python :: 3.4
Classifier: Programming Language :: Python :: 3.5
Classifier: Programming Language :: Python :: 3.6
License-File: LICENSE
Requires-Dist: ovos-plugin-manager<2.0.0,>=0.0.26
Requires-Dist: ovos-bus-client<2.0.0,>=0.0.7
Requires-Dist: ovos-utils<1.0.0,>=0.1.0
Requires-Dist: ovos-workshop<8.0.0,>=2.4.2
Requires-Dist: padacioso<2.0.0,>=0.1.1
Requires-Dist: dbus-next
Provides-Extra: extractors
Requires-Dist: ovos-ocp-youtube-plugin<1.0.0,>=0.0.1; extra == "extractors"
Requires-Dist: ovos-ocp-rss-plugin<1.0.0,>=0.0.2; extra == "extractors"
Requires-Dist: ovos-ocp-m3u-plugin<1.0.0,>=0.0.1; extra == "extractors"
Requires-Dist: ovos-ocp-news-plugin<1.0.0,>=0.1.0; extra == "extractors"
Requires-Dist: ovos-audio-plugin-simple<1.0.0,>=0.0.1; extra == "extractors"
Requires-Dist: ovos-ocp-files-plugin~=0.13; extra == "extractors"
